[
  {
      "Obj_ID":437984,
      "Title":"La Berceuse (Woman Rocking a Cradle; Augustine-Alix Pellicot Roulin, 1851\u20131930)",
      "Img_file":"https://raw.githubusercontent.com/Team-Project-22/image/master/sample_image/437984_Vincent van Gogh_La Berceuse (Woman Rocking a Cradle; Augustine-Alix Pellicot Roulin, 1851\u20131930).jpg?raw=true",
      "Obj_dates":"1889",
      "Dimensions":"36 1\/2 x 29 in. (92.7 x 73.7 cm)",
      "Mediums":"Oil on canvas"
  },
  {
      "Obj_ID":436533,
      "Title":"Shoes",
      "Img_file":"436533_Vincent van Gogh_Shoes.jpg",
      "Obj_dates":"1888",
      "Dimensions":"18 x 21 3\/4 in. (45.7 x 55.2 cm)",
      "Mediums":"Oil on canvas"
  },
  {
      "Obj_ID":436535,
      "Title":"Wheat Field with Cypresses",
      "Img_file":"436535_Vincent van Gogh_Wheat Field with Cypresses.jpg",
      "Obj_dates":"1889",
      "Dimensions":"28 7\/8 \u00d7 36 3\/4 in. (73.2 \u00d7 93.4 cm)",
      "Mediums":"Oil on canvas"
  },
  {
      "Obj_ID":436528,
      "Title":"Irises",
      "Img_file":"436528_Vincent van Gogh_Irises.jpg",
      "Obj_dates":"1890",
      "Dimensions":"29 x 36 1\/4 in. (73.7 x 92.1 cm)",
      "Mediums":"Oil on canvas"
  },
  {
      "Obj_ID":436532,
      "Title":"Self-Portrait with a Straw Hat (obverse: The Potato Peeler)",
      "Img_file":"436532_Vincent van Gogh_Self-Portrait with a Straw Hat (obverse- The Potato Peeler).jpg",
      "Obj_dates":"1887",
      "Dimensions":"16 x 12 1\/2 in. (40.6 x 31.8 cm)",
      "Mediums":"Oil on canvas"
  },
  {
      "Obj_ID":459193,
      "Title":"Road in Etten",
      "Img_file":"459193_Vincent van Gogh_Road in Etten.jpg",
      "Obj_dates":"1881",
      "Dimensions":"15 1\/2 x 22 3\/4 in.  (39.4 x 57.8 cm)",
      "Mediums":"Chalk, pencil, pastel, watercolor.  Underdrawing in pen and brown ink."
  },
  {
      "Obj_ID":436529,
      "Title":"L'Arl\u00e9sienne: Madame Joseph-Michel Ginoux (Marie Julien, 1848\u20131911)",
      "Img_file":"436529_Vincent van Gogh_L'Arl\u00e9sienne- Madame Joseph-Michel Ginoux (Marie Julien, 1848\u20131911).jpg",
      "Obj_dates":"1888\u201389",
      "Dimensions":"36 \u00d7 29 in. (91.4 \u00d7 73.7 cm)",
      "Mediums":"Oil on canvas"
  },
  {
      "Obj_ID":459123,
      "Title":"Madame Roulin and Her Baby",
      "Img_file":"459123_Vincent van Gogh_Madame Roulin and Her Baby.jpg",
      "Obj_dates":"1888",
      "Dimensions":"25 x 20 1\/8 in.",
      "Mediums":"Oil on canvas"
  },
  {
      "Obj_ID":436531,
      "Title":"Peasant Woman Cooking by a Fireplace",
      "Img_file":"436531_Vincent van Gogh_Peasant Woman Cooking by a Fireplace.jpg",
      "Obj_dates":"1885",
      "Dimensions":"17 3\/8 x 15 in. (44.1 x 38.1 cm)",
      "Mediums":"Oil on canvas"
  },
  {
      "Obj_ID":436525,
      "Title":"Bouquet of Flowers in a Vase",
      "Img_file":"436525_Vincent van Gogh_Bouquet of Flowers in a Vase.jpg",
      "Obj_dates":"1890",
      "Dimensions":"25 5\/8 x 21 1\/4 in. (65.1 x 54 cm)",
      "Mediums":"Oil on canvas"
  },
  {
      "Obj_ID":438722,
      "Title":"The Potato Peeler (reverse: Self-Portrait with a Straw Hat)",
      "Img_file":"438722_Vincent van Gogh_The Potato Peeler (reverse- Self-Portrait with a Straw Hat).jpg",
      "Obj_dates":"1885",
      "Dimensions":"16 x 12 1\/2 in. (40.6 x 31.8 cm)",
      "Mediums":"Oil on canvas"
  },
  {
      "Obj_ID":436527,
      "Title":"The Flowering Orchard",
      "Img_file":"436527_Vincent van Gogh_The Flowering Orchard.jpg",
      "Obj_dates":"1888",
      "Dimensions":"28 1\/2 x 21 in. (72.4 x 53.3 cm)",
      "Mediums":"Oil on canvas"
  },
  {
      "Obj_ID":436530,
      "Title":"Oleanders",
      "Img_file":"436530_Vincent van Gogh_Oleanders.jpg",
      "Obj_dates":"1888",
      "Dimensions":"23 3\/4 x 29 in. (60.3 x 73.7 cm)",
      "Mediums":"Oil on canvas"
  },
  {
      "Obj_ID":436534,
      "Title":"Roses",
      "Img_file":"436534_Vincent van Gogh_Roses.jpg",
      "Obj_dates":"1890",
      "Dimensions":"36 5\/8 x 29 1\/8 in. (93 x 74 cm)",
      "Mediums":"Oil on canvas"
  },
  {
      "Obj_ID":436526,
      "Title":"First Steps, after Millet",
      "Img_file":"436526_Vincent van Gogh_First Steps, after Millet.jpg",
      "Obj_dates":"1890",
      "Dimensions":"28 1\/2 x 35 7\/8 in. (72.4 x 91.1 cm)",
      "Mediums":"Oil on canvas"
  },
  {
      "Obj_ID":436524,
      "Title":"Sunflowers",
      "Img_file":"436524_Vincent van Gogh_Sunflowers.jpg",
      "Obj_dates":"1887",
      "Dimensions":"17 x 24 in. (43.2 x 61 cm)",
      "Mediums":"Oil on canvas"
  },
  {
      "Obj_ID":437980,
      "Title":"Cypresses",
      "Img_file":"437980_Vincent van Gogh_Cypresses.jpg",
      "Obj_dates":"1889",
      "Dimensions":"36 3\/4 x 29 1\/8 in. (93.4 x 74 cm)",
      "Mediums":"Oil on canvas"
  },
  {
      "Obj_ID":436536,
      "Title":"Women Picking Olives",
      "Img_file":"436536_Vincent van Gogh_Women Picking Olives.jpg",
      "Obj_dates":"1889",
      "Dimensions":"28 5\/8 x 36 in. (72.7 x 91.4 cm)",
      "Mediums":"Oil on canvas"
  },
  {
      "Obj_ID":437998,
      "Title":"Olive Trees",
      "Img_file":"437998_Vincent van Gogh_Olive Trees.jpg",
      "Obj_dates":"1889",
      "Dimensions":"28 5\/8 x 36 1\/4 in. (72.7 x 92.1 cm)",
      "Mediums":"Oil on canvas"
  },
  {
      "Obj_ID":336327,
      "Title":"Corridor in the Asylum",
      "Img_file":"336327_Vincent van Gogh_Corridor in the Asylum.jpg",
      "Obj_dates":"September 1889",
      "Dimensions":"25 5\/8 x 19 5\/16in. (65.1 x 49.1cm)",
      "Mediums":"Oil color and essence over black chalk on pink laid (\"Ingres\") paper"
  },
  {
      "Obj_ID":849055,
      "Title":"Burning Weeds",
      "Img_file":"849055_Vincent van Gogh_Burning Weeds.jpg",
      "Obj_dates":"mid-July, 1883",
      "Dimensions":"Sheet: 7 1\/4 \u00d7 11 9\/16 in. (18.4 \u00d7 29.3 cm)",
      "Mediums":"Transfer lithograph with pen and ink"
  },
  {
      "Obj_ID":849052,
      "Title":"At Eternity's Gate",
      "Img_file":"849052_Vincent van Gogh_At Eternity's Gate.jpg",
      "Obj_dates":"November 26\u221227, 1882",
      "Dimensions":"Sheet: 23 1\/16 \u00d7 15 3\/8 in. (58.6 \u00d7 39 cm)",
      "Mediums":"Transfer lithograph"
  },
  {
      "Obj_ID":849054,
      "Title":"Gardener by an Apple Tree",
      "Img_file":"849054_Vincent van Gogh_Gardener by an Apple Tree.jpg",
      "Obj_dates":"mid-July, 1883",
      "Dimensions":"Sheet: 9 1\/4 \u00d7 12 11\/16 in. (23.5 \u00d7 32.3 cm)",
      "Mediums":"Transfer lithograph with pen and ink"
  },
  {
      "Obj_ID":849056,
      "Title":"Portrait of Doctor Gachet or Man with a Pipe",
      "Img_file":"849056_Vincent van Gogh_Portrait of Doctor Gachet or Man with a Pipe.jpg",
      "Obj_dates":"1890",
      "Dimensions":"Sheet (folded): 12 13\/16 \u00d7 9 13\/16 in. (32.5 \u00d7 25 cm)",
      "Mediums":"Etching"
  },
  {
      "Obj_ID":335536,
      "Title":"The Zouave",
      "Img_file":"335536_Vincent van Gogh_The Zouave.jpg",
      "Obj_dates":"ca. June 20, 1888",
      "Dimensions":"12 3\/8 x 9 5\/16 in.  (31.5 x 23.6 cm)",
      "Mediums":"Reed pen and brown ink, wax crayon and watercolor, over graphite on wove paper"
  },
  {
      "Obj_ID":335537,
      "Title":"Wheat Field",
      "Img_file":"335537_Vincent van Gogh_Wheat Field.jpg",
      "Obj_dates":"1888",
      "Dimensions":"9 1\/2 x 12 1\/2 in.  (24.1 x 31.7 cm)",
      "Mediums":"Reed pen and logwood ink over graphite on wove paper"
  },
  {
      "Obj_ID":335538,
      "Title":"Nursery on Schenkweg",
      "Img_file":"335538_Vincent van Gogh_Nursery on Schenkweg.jpg",
      "Obj_dates":"April\u2013May 1882",
      "Dimensions":"11 5\/8 x 23 1\/16in. (29.6 x 58.5cm)",
      "Mediums":"Black chalk, graphite, pen, brush, and ink, heightened with white body color on laid paper watermarked ED & CIE (in a cartouche)"
  },
  {
      "Obj_ID":336318,
      "Title":"Street in Saintes-Maries-de-la-Mer",
      "Img_file":"336318_Vincent van Gogh_Street in Saintes-Maries-de-la-Mer.jpg",
      "Obj_dates":"ca. July 15, 1888",
      "Dimensions":"Sheet: 9 9\/16 x 12 1\/2 in. (24.3 x 31.7 cm)",
      "Mediums":"Reed pen, quill, and brown ink over black chalk on wove paper (backed with wove paper)"
  }
]